reliontomotools/__init__.py
reliontomotools/_version.py
reliontomotools/fileIO.py
reliontomotools/motl2relion.py
reliontomotools/relion2motl.py
reliontomotools/utils.py
reliontomotools/warptomo2relion.py
reliontomotools-1.0.0.dist-info/LICENSE
reliontomotools-1.0.0.dist-info/METADATA
reliontomotools-1.0.0.dist-info/WHEEL
reliontomotools-1.0.0.dist-info/entry_points.txt
reliontomotools-1.0.0.dist-info/top_level.txt
reliontomotools-1.0.0.dist-info/RECORD
