Metadata-Version: 2.1
Name: reliontomotools
Version: 1.0.0
Summary: Additional tools for Relion tomo
Home-page: https://github.com/joton/reliontomotools
Author: Joaquín Otón
License: MIT
Project-URL: Bug Tracker, https://github.com/joton/reliontomotools/issues
Classifier: Programming Language :: Python :: 3
Classifier: License :: OSI Approved :: MIT License
Classifier: Operating System :: OS Independent
Requires-Python: >=3.7
License-File: LICENSE
Requires-Dist: numpy
Requires-Dist: pandas
Requires-Dist: xmltodict
Requires-Dist: docopt
Requires-Dist: scipy
Requires-Dist: tqdm
Requires-Dist: transforms3d
Requires-Dist: mrcfile
Requires-Dist: emfile
